jdcat/__init__.py
jdcat/__main__.py
jdcat-1.2.0.data/data/share/jdcat/resources/com.jdcat.proxy.helper.plist
jdcat-1.2.0.data/data/share/jdcat/root_helper/jdcat_proxy_helper.py
jdcat-1.2.0.dist-info/licenses/LICENSE
mitmproxy/local_bridge_addon.py
root_helper/jdcat_proxy_helper.py
sensitive_check_local/__init__.py
sensitive_check_local/analysis_local.py
sensitive_check_local/api.py
sensitive_check_local/assertion_queue.py
sensitive_check_local/autobot_config.py
sensitive_check_local/backend_client.py
sensitive_check_local/cert_manager.py
sensitive_check_local/cli.py
sensitive_check_local/config.py
sensitive_check_local/domain_matcher.py
sensitive_check_local/events.py
sensitive_check_local/jingme_sender.py
sensitive_check_local/network_permission.py
sensitive_check_local/notify_scheduler.py
sensitive_check_local/packaging_utils.py
sensitive_check_local/param_test.py
sensitive_check_local/param_test_execute.py
sensitive_check_local/param_test_executor_queue.py
sensitive_check_local/param_test_throttler.py
sensitive_check_local/process.py
sensitive_check_local/proxy_macos.py
sensitive_check_local/realtime_manager.py
sensitive_check_local/realtime_queue.py
sensitive_check_local/request_modifier_local.py
sensitive_check_local/root_helper_client.py
sensitive_check_local/server.py
sensitive_check_local/status_bar.py
sensitive_check_local/test/test_data_format_fix.py
sensitive_check_local/test/test_data_format_simple.py
sensitive_check_local/test/test_domain_matcher.py
sensitive_check_local/test/test_domain_matching.py
sensitive_check_local/test/test_domain_matching_standalone.py
jdcat-1.2.0.dist-info/METADATA
jdcat-1.2.0.dist-info/WHEEL
jdcat-1.2.0.dist-info/entry_points.txt
jdcat-1.2.0.dist-info/top_level.txt
jdcat-1.2.0.dist-info/RECORD
