Metadata-Version: 2.4
Name: jdcat
Version: 1.2.0
Summary: 支持基础入参测试
Author: Sensitive Check Team
License: MIT
Project-URL: Homepage, https://github.com/sensitive-check/jdcat
Project-URL: Repository, https://github.com/sensitive-check/jdcat
Project-URL: Issues, https://github.com/sensitive-check/jdcat/issues
Keywords: security,proxy,sensitive-data,testing,mitmproxy
Classifier: Development Status :: 4 - Beta
Classifier: Intended Audience :: Developers
Classifier: License :: OSI Approved :: MIT License
Classifier: Programming Language :: Python :: 3
Classifier: Programming Language :: Python :: 3.10
Classifier: Programming Language :: Python :: 3.11
Classifier: Programming Language :: Python :: 3.12
Classifier: Programming Language :: Python :: 3.13
Classifier: Programming Language :: Python :: 3.14
Classifier: Topic :: Security
Classifier: Topic :: Software Development :: Testing
Classifier: Topic :: Internet :: Proxy Servers
Requires-Python: <3.15,>=3.10
License-File: LICENSE
Requires-Dist: typer>=0.12.3
Requires-Dist: PyYAML>=6.0.1
Requires-Dist: fastapi>=0.111.0
Requires-Dist: uvicorn[standard]>=0.23.0
Requires-Dist: httpx>=0.26.0
Requires-Dist: mitmproxy<11.1.0,>=10.0.0
Requires-Dist: rumps>=0.4.0
Dynamic: license-file
